---
title: String的重载加法原理分析
---

## {{ page.title }}

我们知道在执行了

~~~java
    String aa = "aa";
    String bb = aa + "bb"
~~~

之后,bb就变成了字符串"aabb",这片文章通过分析字节码来分析String重载加号的本质。
下面是源代码。

~~~java
    @Test
    public void testStringAdd(){
        String aa = new Random(System.currentTimeMillis()).
        nextBoolean() ? "aa" : "bb";
        
        System.out.println(aa + "123");
    }
~~~

为了防止编译器优化,这里将aa用random来做,有可能aa的值是"aa",也有可能是"bb"。下面编译之后的字节码。

~~~
  public void testStringAdd();
    Code:
       0: new           #2    // class java/util/Random
       3: dup
       4: invokestatic  #3    // Method java/lang/System.currentTimeMillis:()J
       7: invokespecial #4    // Method java/util/Random."<init>":(J)V
      10: invokevirtual #5    // Method java/util/Random.nextBoolean:()Z
      13: ifeq          21
      16: ldc           #6    // String aa
      18: goto          23
      21: ldc           #7    // String bb
      23: astore_1
      24: getstatic     #8    // Field java/lang/System.out:Ljava/io/PrintStream;
      27: new           #9    // class java/lang/StringBuilder
      30: dup
      31: invokespecial #10   // Method java/lang/StringBuilder."<init>":()V
      34: aload_1
      35: invokevirtual #11   // Method java/lang/StringBuilder.append:(Ljava/lang/String;)Ljava/lang/StringBuilder;
      38: ldc           #12   // String 123
      40: invokevirtual #11   // Method java/lang/StringBuilder.append:(Ljava/lang/String;)Ljava/lang/StringBuilder;
      43: invokevirtual #13   // Method java/lang/StringBuilder.toString:()Ljava/lang/String;
      46: invokevirtual #14   // Method java/io/PrintStream.println:(Ljava/lang/String;)V
      49: return
~~~

这些字节码我也看不懂,但是后面的注释真是良心啊,以前怎么没有发现javap原来这么好用啊。可以看到String加法的
实现实际上是通过`StringBuilder`来做的。所以`System.out.println(aa + "123");`实际上等价于下面的代码。

~~~java
    StringBuilder sb = new StringBuilder();
    sb.append(aa);
    sb.append("123");
    System.out.println(sb.toString());
~~~

我好想原来看过有本书里面说的是String的加法重载是通过`StringBuffer`来做的,那`StringBuffer`是线程安全的,效
率会有点低。我这边用的java 1.7,可能是不是在某个版本改了?\\
还有一点,面试的时候被问到字节码完全蒙逼,看来以后的java字节码还要再学习一个啊!
